.travis.yml
AUTHORS
ChangeLog
LICENSE
README.md
constraints.txt
docker-compose.yml
requirements.txt
setup.cfg
setup.py
test-constraints.txt
test-requirements.txt
test-runner.sh
tox.ini
mockserver_friendly/__init__.py
mockserver_friendly_client.egg-info/PKG-INFO
mockserver_friendly_client.egg-info/SOURCES.txt
mockserver_friendly_client.egg-info/dependency_links.txt
mockserver_friendly_client.egg-info/not-zip-safe
mockserver_friendly_client.egg-info/pbr.json
mockserver_friendly_client.egg-info/requires.txt
mockserver_friendly_client.egg-info/top_level.txt
test/__init__.py
test/test_basic_expectations.py
test/test_basic_responses.py
test/test_basic_stubbing.py
test/test_basic_verifying.py
test/test_delays.py
test/test_form_requests.py
test/test_json_requests.py
test/test_json_response.py